qairt_wrapper/__init__.py
qairt_wrapper/qairt_wrapper.py
qairt_wrapper-1.0.7.dist-info/licenses/LICENSE
qairt_wrapper-1.0.7.dist-info/METADATA
qairt_wrapper-1.0.7.dist-info/WHEEL
qairt_wrapper-1.0.7.dist-info/top_level.txt
qairt_wrapper-1.0.7.dist-info/RECORD
