Metadata-Version: 2.4
Name: qairt-wrapper
Version: 1.0.7
Summary: A Python wrapper for Qualcomm QAIRT SDK
Author-email: linbaichuan <iamlbc2525@163.com>
License: MIT
Classifier: Programming Language :: Python :: 3
Classifier: License :: OSI Approved :: MIT License
Classifier: Operating System :: OS Independent
Requires-Python: >=3.7
License-File: LICENSE
Requires-Dist: numpy
Dynamic: license-file
